[
    {
        "label": "search",
        "start": "2025-05-04 23:01:54.788598",
        "end": "2025-05-04 23:02:02.728996"
    },
    {
        "label": "processing results",
        "start": "2025-05-04 23:02:02.728395",
        "end": "2025-05-04 23:02:02.728963"
    },
    {
        "label": "collecting ids",
        "start": "2025-05-04 23:02:02.728342",
        "end": "2025-05-04 23:02:02.728383"
    },
    {
        "label": "run job # 0",
        "start": "2025-05-04 23:01:54.789197",
        "end": "2025-05-04 23:02:02.712731"
    },
    {
        "label": "start job # 0",
        "start": "2025-05-04 23:01:54.788749",
        "end": "2025-05-04 23:01:54.789116"
    },
    {
        "label": "submitting job # 0",
        "start": "2025-05-04 23:01:54.788735",
        "end": "2025-05-04 23:01:54.789088"
    },
    {
        "label": "thread pool create",
        "start": "2025-05-04 23:01:54.788628",
        "end": "2025-05-04 23:01:54.788660"
    }
]